toolforge/__init__.py
toolforge/exceptions.py
toolforge/py.typed
toolforge-6.1.0.dist-info/METADATA
toolforge-6.1.0.dist-info/WHEEL
toolforge-6.1.0.dist-info/licenses/COPYING
toolforge-6.1.0.dist-info/RECORD
