Metadata-Version: 2.4
Name: toolforge
Version: 6.1.0
Summary: Small library for common tasks on Wikimedia Toolforge
Project-URL: Documentation, https://python-toolforge.readthedocs.io/
Project-URL: Changelog, https://gitlab.wikimedia.org/toolforge-repos/python-toolforge/-/blob/main/HISTORY.rst
Project-URL: Bug Tracker, https://phabricator.wikimedia.org/tag/tool-python-toolforge/
Project-URL: Source, https://gitlab.wikimedia.org/toolforge-repos/python-toolforge
Author-email: Kunal Mehta <Legoktm@debian.org>
Maintainer-email: Bryan Davis <bd808@wikimedia.org>, Lucas Werkmeister <mail@lucaswerkmeister.de>
License-Expression: GPL-3.0+
License-File: COPYING
Keywords: toolforge,wikimedia
Classifier: Development Status :: 5 - Production/Stable
Classifier: Intended Audience :: Developers
Classifier: License :: OSI Approved :: GNU General Public License v3 or later (GPLv3+)
Classifier: Programming Language :: Python :: 3
Classifier: Programming Language :: Python :: 3 :: Only
Classifier: Programming Language :: Python :: 3.7
Classifier: Programming Language :: Python :: 3.8
Classifier: Programming Language :: Python :: 3.9
Classifier: Programming Language :: Python :: 3.10
Classifier: Programming Language :: Python :: 3.11
Classifier: Programming Language :: Python :: 3.12
Classifier: Programming Language :: Python :: 3.13
Classifier: Topic :: Software Development :: Libraries
Requires-Python: >=3.7
Requires-Dist: decorator>=5.1.1
Requires-Dist: pymysql>=1.0.3
Requires-Dist: requests>=2.28.2
